{
  "generated": "2026-06-11T21:57:19.257718+09:00",
  "items": [
    {
      "keyword": "빚투(레버리지 투자)",
      "category": "정책",
      "weight": 9,
      "stocks": [],
      "news": [
        {
          "title": "5월 가계대출 9조3천억 증가…‘빚투’에 신용대출 3조4천억↑",
          "url": "http://www.fnnews.com/news/202606111843032440"
        },
        {
          "title": "'빚투'에 5월 가계대출 9.3兆 늘었다 ‥고연봉 신용대출 한도 줄어드나",
          "url": "http://www.fnnews.com/news/202606111356429942"
        },
        {
          "title": "반도체株로 몰린 빚투, 반대매매 1조 돌파..금감원, 쏠림투자 경고",
          "url": "https://kpenews.com/View.aspx?No=4108897"
        }
      ],
      "streak": 1
    },
    {
      "keyword": "외국인 매도",
      "category": "섹터",
      "weight": 9,
      "stocks": [],
      "news": [
        {
          "title": "[마감시황] 코스피, 7800선 턱걸이…'30만전자' 무너졌지만 외국인 반도...",
          "url": "http://www.kdfnews.com/news/articleView.html?idxno=184143"
        },
        {
          "title": "[개장시황] 외국인 '팔자'에 코스피 장 초반 4%대 급락",
          "url": "https://www.newspim.com/news/view/20260611000209"
        },
        {
          "title": "24일째 순매도 외국인…삼전·닉스 '차익실현' 언제 끝날까",
          "url": "https://www.sidae.com/article/2026061114114894024"
        }
      ],
      "streak": 1
    },
    {
      "keyword": "반도체 주가 변동성",
      "category": "섹터",
      "weight": 9,
      "stocks": [
        "삼성전자",
        "SK하이닉스"
      ],
      "news": [
        {
          "title": "삼성전자 주가 30만원선 붕괴, SK하이닉스 반등...외국인 매수 전환 영향",
          "url": "https://www.tokenpost.kr/news/market/368256"
        },
        {
          "title": "변동성 키우는 ‘삼전·닉스 레버리지’ 리스크도 커졌다",
          "url": "https://www.khan.co.kr/article/202606112037055"
        },
        {
          "title": "삼성전자, 글로벌 전략회의 돌입 … 파운드리·세트 새판 짠다",
          "url": "https://biz.newdaily.co.kr/site/data/html/2026/06/11/2026061100300.html"
        }
      ],
      "streak": 1
    },
    {
      "keyword": "변동성 확대(롤러코스터)",
      "category": "거시",
      "weight": 8,
      "stocks": [],
      "news": [
        {
          "title": "[퇴근길머니] 7,700선 지켜낸 코스피…롤러코스피에 거래 '꽁꽁'",
          "url": "http://www.yonhapnewstv.co.kr/news/MYH20260611173442i9W"
        },
        {
          "title": "하루 400P 롤러코스터…코스피 7763.95 강보합 마감",
          "url": "https://www.mt.co.kr/stock/2026/06/11/2026061115581419103"
        },
        {
          "title": "코스피 하루 변동 폭 '400포인트'",
          "url": "http://www.econotelling.com/news/articleView.html?idxno=20645"
        }
      ],
      "streak": 1
    },
    {
      "keyword": "중동 리스크",
      "category": "거시",
      "weight": 8,
      "stocks": [],
      "news": [
        {
          "title": "결국 '상승 마감' 지켜낸 코스피...중동 리스크도 완화 [fn마감시황]",
          "url": "http://www.fnnews.com/news/202606111557589158"
        },
        {
          "title": "[이 시각 시황] 이란, 호르무즈 해협 전면 차단 선언…해운주 '들썩'",
          "url": "https://biz.sbs.co.kr/article_hub/20000315831?division=NAVER"
        },
        {
          "title": "중동사태 장기화로 주력산업 제조·건설업 ‘고용 쇼크’",
          "url": "https://www.segye.com/newsView/20260611516218?OutUrl=naver"
        }
      ],
      "streak": 1
    },
    {
      "keyword": "개인 매수",
      "category": "섹터",
      "weight": 8,
      "stocks": [],
      "news": [
        {
          "title": "[마감시황] 코스피, 개인 '사자'에 7700선 강보합…코스닥 4%대↑",
          "url": "https://www.shinailbo.co.kr/news/articleView.html?idxno=5029743"
        },
        {
          "title": "‘상승·하락 50여차례’ 갈팡질팡 코스피…초고수들은 ‘삼전’ 집중 ...",
          "url": "https://biz.heraldcorp.com/article/10769968?ref=naver"
        },
        {
          "title": "코스피, 7760선 턱걸이 상승 마감...개인 2조 순매수에 하루 만에 반등",
          "url": "https://www.pinpointnews.co.kr/news/articleView.html?idxno=459462"
        }
      ],
      "streak": 1
    },
    {
      "keyword": "삼성전자 미공개정보 이용",
      "category": "종목",
      "weight": 8,
      "stocks": [
        "삼성전자"
      ],
      "news": [
        {
          "title": "검찰, 삼성전자 수원 본사 압수수색...\"레인보우로보틱스 인수 미공개 ...",
          "url": "https://www.livebiz.today/news/articleView.html?idxno=202587"
        },
        {
          "title": "검찰, 삼성전자 본사 압수수색 미공개 정보 이용 주식 거래 혐의",
          "url": "https://www.jnilbo.com/news/articleView.html?idxno=90000041764"
        },
        {
          "title": "검찰 '미공개 정보 이용 혐의' 삼성전자 본사 압수수색",
          "url": "https://www.safetimes.co.kr/news/articleView.html?idxno=243431"
        }
      ],
      "streak": 1
    },
    {
      "keyword": "반대매매 증가",
      "category": "정책",
      "weight": 7,
      "stocks": [],
      "news": [
        {
          "title": "반대매매 2년8개월 만에 최고…'레버리지 리스크' 다시 부각",
          "url": "https://www.greened.kr/news/articleView.html?idxno=342307"
        },
        {
          "title": "반도체株로 몰린 빚투, 반대매매 1조 돌파..금감원, 쏠림투자 경고",
          "url": "https://kpenews.com/View.aspx?No=4108897"
        },
        {
          "title": "‘강제로 내 주식이 팔렸다’ 함부로 했다간 빚더미…‘초단기 빚투’...",
          "url": "https://biz.heraldcorp.com/article/10769765?ref=naver"
        }
      ],
      "streak": 1
    },
    {
      "keyword": "신용대출 급증",
      "category": "거시",
      "weight": 7,
      "stocks": [],
      "news": [
        {
          "title": "5월 가계대출 9조3천억 증가…‘빚투’에 신용대출 3조4천억↑",
          "url": "http://www.fnnews.com/news/202606111843032440"
        },
        {
          "title": "'빚투'에 5월 가계대출 9.3兆 늘었다 ‥고연봉 신용대출 한도 줄어드나",
          "url": "http://www.fnnews.com/news/202606111356429942"
        },
        {
          "title": "증시 ‘빚투’ 폭발, 은행 신용·마이너스 대출 증가폭 5년만에 최대··...",
          "url": "https://www.khan.co.kr/article/202606111639001"
        }
      ],
      "streak": 1
    },
    {
      "keyword": "원달러 환율 상승",
      "category": "거시",
      "weight": 7,
      "stocks": [],
      "news": [
        {
          "title": "원 달러 환율, 장중 1530원 '터치'",
          "url": "https://www.idaegu.co.kr/news/articleView.html?idxno=550845"
        },
        {
          "title": "'V자 반등' 코스피 7,760선 안착, 원·달러 환율은 1,528.9원으로 상승 마...",
          "url": "https://www.businesskorea.co.kr/news/articleView.html?idxno=271128"
        },
        {
          "title": "[외환-마감] 외인 주식 '팔자' 행렬에 상승…4.70원↑",
          "url": "https://news.einfomax.co.kr/news/articleView.html?idxno=4419563"
        }
      ],
      "streak": 1
    },
    {
      "keyword": "AI 전략 실행",
      "category": "섹터",
      "weight": 7,
      "stocks": [
        "네이버",
        "삼성전자"
      ],
      "news": [
        {
          "title": "[미리보는 이데일리 신문]국가 AI전략 중심축 '네이버 사단'이 떴다",
          "url": "https://www.edaily.co.kr/news/newspath.asp?newsid=06901126645480736"
        },
        {
          "title": "엔비디아 자율주행칩 품는 삼성 파운드리…TSMC 병목에 '흑자 전환' 전망...",
          "url": "http://www.inews24.com/view/1975920"
        },
        {
          "title": "[현장] \"AI 올라탄 자 231조 쓸어담았다\"… 대한민국 50대 브랜드 성적 ...",
          "url": "https://www.nbntv.co.kr/news/articleView.html?idxno=4022263"
        }
      ],
      "streak": 1
    },
    {
      "keyword": "HBM/파운드리 경쟁",
      "category": "섹터",
      "weight": 7,
      "stocks": [
        "SK하이닉스",
        "삼성전자"
      ],
      "news": [
        {
          "title": "엔비디아 자율주행칩 품는 삼성 파운드리…TSMC 병목에 '흑자 전환' 전망...",
          "url": "http://www.inews24.com/view/1975920"
        },
        {
          "title": "삼성전자, 글로벌 전략회의 돌입 … 파운드리·세트 새판 짠다",
          "url": "https://biz.newdaily.co.kr/site/data/html/2026/06/11/2026061100300.html"
        },
        {
          "title": "SK하이닉스, HBM 시장 독주 속 임원 자사주 매각…시장 우려 교차",
          "url": "https://www.mdtoday.co.kr/news/articleView.html?idxno=600530"
        }
      ],
      "streak": 1
    },
    {
      "keyword": "코스닥 급등",
      "category": "거시",
      "weight": 7,
      "stocks": [],
      "news": [
        {
          "title": "코스피·코스닥 동반 상승…널뛰기 장세 속 훈풍 [마감시황]",
          "url": "https://www.ekn.kr/web/view.php?key=20260611026392552"
        },
        {
          "title": "[마감시황] 코스피, 장중 7400선 붕괴 딛고 강보합 마감…코스닥 4.76% 급...",
          "url": "https://www.ajunews.com/view/20260611161142906"
        },
        {
          "title": "하루새 400포인트 오간 코스피 강보합 마감…코스닥은 5% 가까이↑",
          "url": "https://www.dnews.co.kr/uhtml/view.jsp?idxno=202606111650075450077"
        }
      ],
      "streak": 1
    },
    {
      "keyword": "스페이스X 상장 자금 유출",
      "category": "거시",
      "weight": 6,
      "stocks": [],
      "news": [
        {
          "title": "스페이스X 상장 D-1… 코스피 흔든 '자금 블랙홀' 연말까지 이어질까",
          "url": "https://www.hankookilbo.com/news/article/A2026061114280000913?did=NA"
        },
        {
          "title": "'네 마녀의 날' 넘긴 코스피…유럽금리·스페이스X 산 넘어 산",
          "url": "https://www.mt.co.kr/stock/2026/06/11/2026061117393056190"
        },
        {
          "title": "뉴욕증시 프리뷰, 반도체주 반등에 미 주가지수 선물 상승…유가 하락·...",
          "url": "https://www.newspim.com/news/view/20260611001187"
        }
      ],
      "streak": 1
    },
    {
      "keyword": "투자경고/공매도 과열 종목",
      "category": "정책",
      "weight": 6,
      "stocks": [
        "인탑스"
      ],
      "news": [
        {
          "title": "'공매도 과열 종목'으로 잇따라 지정되는 인탑스의 기현상 왜?",
          "url": "https://www.ilemonde.com/news/articleView.html?idxno=30154"
        },
        {
          "title": "대원전선, 투자경고종목 지정해제→재지정 예고",
          "url": "https://www.topstarnews.net/news/articleView.html?idxno=16088623"
        },
        {
          "title": "코스모로보틱스, 공매도 금지 연장→투자 경계령",
          "url": "https://www.topstarnews.net/news/articleView.html?idxno=16088617"
        }
      ],
      "streak": 1
    }
  ]
}